Metadata-Version: 1.1
Name: ptwinrm
Version: 0.1.0
Summary: winrm console
Home-page: https://github.com/tiagocoutinho/ptwinrm
Author: Tiago Coutinho
Author-email: coutinhotiago@gmail.com
License: MIT
Keywords: windows winrm console
Platform: UNKNOWN
Classifier: Programming Language :: Python
Classifier: Programming Language :: Python :: 2.6
Classifier: Programming Language :: Python :: 2.7
Classifier: Programming Language :: Python :: 3.4
Classifier: Programming Language :: Python :: 3.5
Classifier: Programming Language :: Python :: 3.6
